solidipes_core_plugin/__init__.py
solidipes_core_plugin/downloaders/__init__.py
solidipes_core_plugin/downloaders/dspace5.py
solidipes_core_plugin/downloaders/dspace7.py
solidipes_core_plugin/downloaders/dtool.py
solidipes_core_plugin/downloaders/git.py
solidipes_core_plugin/downloaders/rclone.py
solidipes_core_plugin/downloaders/zenodo.py
solidipes_core_plugin/loaders/__init__.py
solidipes_core_plugin/loaders/code_snippet.py
solidipes_core_plugin/loaders/gnuplot.py
solidipes_core_plugin/loaders/hdf5.py
solidipes_core_plugin/loaders/image.py
solidipes_core_plugin/loaders/image_sequence.py
solidipes_core_plugin/loaders/json.py
solidipes_core_plugin/loaders/matlab.py
solidipes_core_plugin/loaders/notebook.py
solidipes_core_plugin/loaders/pdf.py
solidipes_core_plugin/loaders/python_pickle.py
solidipes_core_plugin/loaders/rdf.py
solidipes_core_plugin/loaders/table.py
solidipes_core_plugin/loaders/text.py
solidipes_core_plugin/loaders/tikz.py
solidipes_core_plugin/loaders/video.py
solidipes_core_plugin/loaders/xml.py
solidipes_core_plugin/loaders/yaml.py
solidipes_core_plugin/mounters/__init__.py
solidipes_core_plugin/mounters/dtool.py
solidipes_core_plugin/mounters/juicefs.py
solidipes_core_plugin/mounters/rclone.py
solidipes_core_plugin/mounters/s3.py
solidipes_core_plugin/mounters/sshfs.py
solidipes_core_plugin/mounters/unix_mount.py
solidipes_core_plugin/reports/__init__.py
solidipes_core_plugin/reports/jtcam.py
solidipes_core_plugin/reports/jtcam_small_logo.png
solidipes_core_plugin/reports/jupyter_logo.png
solidipes_core_plugin/reports/web_report.py
solidipes_core_plugin/reports/widgets/__init__.py
solidipes_core_plugin/reports/widgets/custom_widgets.py
solidipes_core_plugin/reports/widgets/display_file.py
solidipes_core_plugin/reports/widgets/dspace.py
solidipes_core_plugin/reports/widgets/dtool.py
solidipes_core_plugin/reports/widgets/file_button.py
solidipes_core_plugin/reports/widgets/file_list.py
solidipes_core_plugin/reports/widgets/front_page.py
solidipes_core_plugin-0.0.39.dist-info/licenses/LICENSE
solidipes_core_plugin-0.0.39.dist-info/METADATA
solidipes_core_plugin-0.0.39.dist-info/WHEEL
solidipes_core_plugin-0.0.39.dist-info/entry_points.txt
solidipes_core_plugin-0.0.39.dist-info/top_level.txt
solidipes_core_plugin-0.0.39.dist-info/RECORD
