Metadata-Version: 2.4
Name: solidipes-core-plugin
Version: 0.0.39
Summary: Core plugin for Solidipes with essential modular components
Author-email: Son Pham-Ba <son.phamba@epfl.ch>, Guillaume Anciaux <guillaume.anciaux@epfl.ch>
License: GPL-3.0-or-later
Requires-Python: <3.13,>=3.10
License-File: LICENSE
Requires-Dist: cairosvg~=2.7.0
Requires-Dist: datasize~=1.0.0
Requires-Dist: h5py~=3.13.0
Requires-Dist: ipython~=8.18.1
Requires-Dist: matplotlib>=3.7.1
Requires-Dist: nbconvert~=7.16.4
Requires-Dist: openpyxl~=3.1.5
Requires-Dist: pylint~=3.1.0
Requires-Dist: python-gitlab~=5.6.0
Requires-Dist: rdflib~=7.1.1
Requires-Dist: streamlit~=1.45.0
Requires-Dist: streamlit-ace~=0.1.1
Requires-Dist: streamlit-aggrid<=1.1.2
Requires-Dist: streamlit-editable-list~=0.0.6
Requires-Dist: streamlit-tree-select~=0.0.5
Requires-Dist: streamlit-quill~=0.0.3
Requires-Dist: xmltodict~=0.13.0
Requires-Dist: streamlit-scrollable-textbox>=0.0.3
Requires-Dist: tqdm>=4.67.1
Requires-Dist: dtoolcore~=3.19.0
Requires-Dist: dtool-s3~=0.14.1
Provides-Extra: dev
Requires-Dist: cheroot>=11.0.0; extra == "dev"
Requires-Dist: pre-commit~=4.1.0; extra == "dev"
Requires-Dist: pytest~=8.1.1; extra == "dev"
Requires-Dist: pytest-cov~=5.0.0; extra == "dev"
Requires-Dist: requests-mock~=1.10.0; extra == "dev"
Requires-Dist: tomli>=2.2.1; extra == "dev"
Requires-Dist: wsgidav>=4.3.3; extra == "dev"
Provides-Extra: test
Requires-Dist: cheroot>=11.0.0; extra == "test"
Requires-Dist: pytest~=8.1.1; extra == "test"
Requires-Dist: pytest-cov~=5.0.0; extra == "test"
Requires-Dist: requests-mock~=1.10.0; extra == "test"
Requires-Dist: tomli>=2.2.1; extra == "test"
Requires-Dist: wsgidav>=4.3.3; extra == "test"
Dynamic: license-file
